croquemort/__init__.py
croquemort/crawler.py
croquemort/decorators.py
croquemort/http.py
croquemort/logger.py
croquemort/migrations.py
croquemort/reports.py
croquemort/storages.py
croquemort/timer.py
croquemort/tools.py
croquemort/webhook.py
croquemort/templates/report.html
tests/__init__.py
tests/conftest.py
tests/example_csv.py
tests/test_integrations.py
tests/test_storages.py
tests/test_tools.py
tests/test_urls.py
tests/utils.py
tests/services/__init__.py
tests/services/test_crawler.py
tests/services/test_http.py
tests/services/test_webhook.py
croquemort-2.1.0.dist-info/LICENSE
croquemort-2.1.0.dist-info/METADATA
croquemort-2.1.0.dist-info/WHEEL
croquemort-2.1.0.dist-info/top_level.txt
croquemort-2.1.0.dist-info/RECORD
