Metadata-Version: 2.1
Name: croquemort
Version: 2.1.0
Summary: Croquemort linkchecker
Home-page: https://github.com/opendatateam/croquemort
Author: Opendata Team
Author-email: opendatateam@data.gouv.fr
License: MIT
Keywords: linkchecker croquemort
Platform: UNKNOWN
Classifier: Development Status :: 4 - Beta
Classifier: Programming Language :: Python
Classifier: Environment :: Web Environment
Classifier: Operating System :: OS Independent
Classifier: Intended Audience :: Developers
Classifier: Topic :: System :: Software Distribution
Classifier: Topic :: Software Development :: Libraries :: Python Modules
Classifier: Programming Language :: Python
Classifier: Programming Language :: Python :: 3
Classifier: Programming Language :: Python :: 3.5
Classifier: Programming Language :: Python :: 3.6
Classifier: License :: OSI Approved :: MIT License
Requires-Dist: Jinja2 (==2.10.1)
Requires-Dist: redis (==3.2.1)
Requires-Dist: nameko (==2.12.0)
Requires-Dist: wrapt (==1.11.1)
Requires-Dist: validators (==0.12.5)
Provides-Extra: test
Requires-Dist: requests-mock (==1.6.0) ; extra == 'test'
Requires-Dist: pytest (==4.4.1) ; extra == 'test'
